Workbook

Sheet Assumptions
A1: Lumeo Analytics — FY2026 Operating Model Assumptions
A2: Starting customers (Jan) | B2: 220
A3: Monthly growth rate | B3: 0.08
A4: Monthly churn rate | B4: 0.03
A5: Price per seat / month ($) | B5: 99
A6: CAC — cost per new customer ($) | B6: 1150
A8: Monthly payroll ($) | B8: 185000
A9: Office & misc ($ / month) | B9: 22000
A10: Infra cost per customer ($ / month) | B10: 11
A11: Starting cash ($) | B11: 2400000
A12: Support cost per customer ($ / month) | B12: 6
Z99: pytest-36ed53

Sheet Revenue
A1: Revenue Build
A2: Month | B2: Jan | C2: Feb | D2: Mar | E2: Apr | F2: May | G2: Jun | H2: Jul | I2: Aug | J2: Sep | K2: Oct | L2: Nov | M2: Dec
A3: Customers (EOM) | B3: =Assumptions!B2 | C3: =ROUND(B3*(1+Assumptions!$B$3-Assumptions!$B$4),0) | D3: =ROUND(C3*(1+Assumptions!$B$3-Assumptions!$B$4),0) | E3: =ROUND(D3*(1+Assumptions!$B$3-Assumptions!$B$4),0) | F3: =ROUND(E3*(1+Assumptions!$B$3-Assumptions!$B$4),0) | G3: =ROUND(F3*(1+0.15-Assumptions!$B$4),0) | H3: =ROUND(G3*(1+Assumptions!$B$3-Assumptions!$B$4),0) | I3: =ROUND(H3*(1+Assumptions!$B$3-Assumptions!$B$4),0) | J3: =ROUND(I3*(1+Assumptions!$B$3-Assumptions!$B$4),0) | K3: =ROUND(J3*(1+Assumptions!$B$3-Assumptions!$B$4),0) | L3: =ROUND(K3*(1+Assumptions!$B$3-Assumptions!$B$4),0) | M3: =ROUND(L3*(1+Assumptions!$B$3-Assumptions!$B$4),0)
A4: New customers | B4: =ROUND(Assumptions!B2*Assumptions!$B$3,0) | C4: =ROUND(B3*Assumptions!$B$3,0) | D4: =ROUND(C3*Assumptions!$B$3,0) | E4: =ROUND(D3*Assumptions!$B$3,0) | F4: =ROUND(E3*Assumptions!$B$3,0) | G4: =ROUND(F3*Assumptions!$B$3,0) | H4: =ROUND(G3*Assumptions!$B$3,0) | I4: =ROUND(H3*Assumptions!$B$3,0) | J4: =ROUND(I3*Assumptions!$B$3,0) | ... M4: =ROUND(L3*Assumptions!$B$3,0)
A5: MRR ($) | B5: =B3*Assumptions!$B$5 | C5: =C3*Assumptions!$B$5 | D5: =D3*Assumptions!$B$5 | E5: =E3*Assumptions!$B$5 | F5: =F3*Assumptions!$B$5 | G5: =G3*Assumptions!$B$5 | H5: =H3*Assumptions!$B$5 | I5: =I3*Assumptions!$B$5 | J5: =J3*Assumptions!$B$5 | K5: 34452 | L5: =L3*Assumptions!$B$5 | M5: =M3*Assumptions!$B$5
A6: ARR run-rate ($) | B6: =B5*12 | C6: =C5*12 | D6: =D5*12 | E6: =E5*12 | F6: =F5*12 | G6: =G5*12 | H6: =H5*12 | I6: =I5*12 | ... M6: =M5*12

Sheet Costs
A1: Cost Build
A2: Month | B2: Jan | C2: Feb | D2: Mar | E2: Apr | F2: May | G2: Jun | H2: Jul | I2: Aug | J2: Sep | K2: Oct | L2: Nov | M2: Dec
A3: Payroll ($) | B3: =Assumptions!$B$8 | C3: =Assumptions!$B$8 | D3: =Assumptions!$B$8 | E3: =Assumptions!$B$8 | F3: =Assumptions!$B$8 | G3: =Assumptions!$B$8 | H3: =Assumptions!$B$8 | I3: =Assumptions!$B$8 | ... M3: =Assumptions!$B$8
A4: Marketing / CAC ($) | B4: =Revenue!B4*Assumptions!$B$6 | C4: =Revenue!C4*Assumptions!$B$6 | D4: =Revenue!D4*Assumptions!$B$6 | E4: =Revenue!E4*Assumptions!$B$6 | F4: =Revenue!F4*Assumptions!$B$6 | G4: =Revenue!G4*Assumptions!$B$6 | H4: =Revenue!H4*Assumptions!$B$6 | I4: =Revenue!I4*Assumptions!$B$6 | ... M4: =Revenue!M4*Assumptions!$B$6
A5: Infrastructure ($) | B5: =Revenue!B3*Assumptions!$B$10 | C5: =Revenue!C3*Assumptions!$B$10 | D5: =Revenue!D3*Assumptions!$B$10 | E5: =Revenue!E3*Assumptions!$B$10 | F5: =Revenue!F3*Assumptions!$B$10 | G5: =Revenue!G3*Assumptions!$B$10 | H5: =Revenue!H3*Assumptions!$B$10 | I5: =Revenue!I3*Assumptions!$B$10 | ... M5: =Revenue!M3*Assumptions!$B$10
A6: Office & misc ($) | B6: =Assumptions!$B$9 | C6: =Assumptions!$B$9 | D6: =Assumptions!$B$9 | E6: =Assumptions!$B$9 | F6: =Assumptions!$B$9 | G6: =Assumptions!$B$9 | H6: =Assumptions!$B$9 | I6: =Assumptions!$B$9 | ... M6: =Assumptions!$B$9
A7: Contractors & one-time ($) | B7: 0 | C7: 0 | D7: 15000 | E7: 0 | F7: 0 | G7: 0 | H7: 8000 | I7: 0 | J7: 0 | K7: 12000 | L7: 0 | M7: 0
A8: Total costs ($) | B8: =SUM(B3:B6) | C8: =SUM(C3:C6) | D8: =SUM(D3:D6) | E8: =SUM(E3:E6) | F8: =SUM(F3:F6) | G8: =SUM(G3:G6) | H8: =SUM(H3:H6) | I8: =SUM(I3:I6) | ... M8: =SUM(M3:M6)

Sheet Summary
A1: Board Summary — FY2026
A3: Total FY2026 revenue ($) | B3: =SUM(Revenue!B5:M5)
A4: Total FY2026 costs ($) | B4: =SUM(Costs!B8:M8)
A5: Net income ($) | B5: =B3-B4
A6: Ending cash ($) | B6: =Assumptions!B11+B5
A7: Avg monthly burn ($) | B7: =(B4-B3)/12
A8: Runway (months) | B8: =IF(B5>0,"Profitable",Assumptions!B11/((B4-B3)/12))
A10: Dec ARR — exit run-rate ($) | B10: =Revenue!L6
A11: Customers at exit | B11: =Revenue!M3
